Verilog_Programming/FullSubtractor.v
// Difference = A ^ B ^ Bin
// Bout = ~ABin + ~AB + BBin

module FullSub (
    input wire a,b,bin,
    output wire diff,bo
);

    assign diff = a^b^bin;
    assign bo = (~a&b)| (~a&bin) | (b&bin);
    
endmodule

module TB;

    reg a,b,bin;
    wire d,bo;

    FullSub uut (.a(a),.b(b),.bin(bin),.diff(d),.bo(bo));

    initial begin
        a=0;b=0;bin=0;#10;
        a=0;b=0;bin=1;#10;
        a=0;b=1;bin=0;#10;
        a=0;b=1;bin=1;#10;
        a=1;b=0;bin=0;#10;
        a=1;b=0;bin=1;#10;
        a=1;b=1;bin=0;#10;
        a=1;b=1;bin=1;#10;
    end

    initial begin
        $dumpfile("output.vcd");
        $dumpvars(0,TB);
    end
    
endmodule

Verilog_Programming/output.vcd
$date
	Sat Mar 22 23:52:12 2025
$end
$version
	Icarus Verilog
$end
$timescale
	1s
$end
$scope module TB $end
$var wire 1 ! d $end
$var wire 1 " bo $end
$var reg 1 # a $end
$var reg 1 $ b $end
$var reg 1 % bin $end
$scope module uut $end
$var wire 1 # a $end
$var wire 1 $ b $end
$var wire 1 % bin $end
$var wire 1 " bo $end
$var wire 1 ! diff $end
$upscope $end
$upscope $end
$enddefinitions $end
$comment Show the parameter values. $end
$dumpall
$end
#0
$dumpvars
0%
0$
0#
0"
0!
$end
#10
1"
1!
1%
#20
0%
1$
#30
0!
1%
#40
0"
1!
0%
0$
1#
#50
0!
1%
#60
0%
1$
#70
1"
1!
1%
